python_docstring_markdown-0.4.0.dist-info/METADATA
python_docstring_markdown-0.4.0.dist-info/WHEEL
python_docstring_markdown-0.4.0.dist-info/entry_points.txt
python_docstring_markdown-0.4.0.dist-info/licenses/LICENSE
python_docstring_markdown/__init__.py
python_docstring_markdown/__main__.py
python_docstring_markdown/generate.py
python_docstring_markdown-0.4.0.dist-info/RECORD
