Metadata-Version: 2.1
Name: python-docstring-markdown
Version: 0.4.0
Summary: Generates Markdown documentation from Python module dosctrings
Author-Email: Chris Riccomini <criccomini@apache.org>
License: CC-0
Project-URL: documentation, https://github.com/criccomini/python-docstring-markdown/blob/main/DOCUMENTATION.md
Project-URL: repository, https://github.com/criccomini/python-docstring-markdown
Project-URL: issues, https://github.com/criccomini/python-docstring-markdown/issues
Requires-Python: >=3.10
Requires-Dist: docstring-parser-fork>=0.0.12
